invenio_explicit_acls/__init__.py
invenio_explicit_acls/acl_records_search.py
invenio_explicit_acls/admin.py
invenio_explicit_acls/api.py
invenio_explicit_acls/cli.py
invenio_explicit_acls/config.py
invenio_explicit_acls/es.py
invenio_explicit_acls/ext.py
invenio_explicit_acls/marshmallow.py
invenio_explicit_acls/models.py
invenio_explicit_acls/permissions.py
invenio_explicit_acls/proxies.py
invenio_explicit_acls/record.py
invenio_explicit_acls/serializers.py
invenio_explicit_acls/signals.py
invenio_explicit_acls/tasks.py
invenio_explicit_acls/utils.py
invenio_explicit_acls/version.py
invenio_explicit_acls/acls/__init__.py
invenio_explicit_acls/acls/default_acls.py
invenio_explicit_acls/acls/elasticsearch_acls.py
invenio_explicit_acls/acls/es_mixin.py
invenio_explicit_acls/acls/id_acls.py
invenio_explicit_acls/acls/propertyvalue_acls.py
invenio_explicit_acls/actors/__init__.py
invenio_explicit_acls/actors/mixins.py
invenio_explicit_acls/actors/record_role.py
invenio_explicit_acls/actors/record_user.py
invenio_explicit_acls/actors/role.py
invenio_explicit_acls/actors/system_role.py
invenio_explicit_acls/actors/user.py
invenio_explicit_acls/alembic/06aae02f41ca_timestamped_actors.py
invenio_explicit_acls/alembic/21ab0d49a6ca_propertyvalueacl.py
invenio_explicit_acls/alembic/2cd83b6065cc_name_on_actors.py
invenio_explicit_acls/alembic/5ba4aa9a23ba_document_based_acls.py
invenio_explicit_acls/alembic/854a5351f76f_added_priority_group.py
invenio_explicit_acls/alembic/d179cf16d686_propertyvalueacl.py
invenio_explicit_acls/alembic/e1f135387190_systemrole_actor.py
invenio_explicit_acls/alembic/ec5cbec43ec8_initial_layout.py
invenio_explicit_acls/mappings/mixins/v6/invenio-acl-mixin-v1.0.0.json
invenio_explicit_acls/mappings/mixins/v7/invenio-acl-mixin-v1.0.0.json
invenio_explicit_acls-4.5.0.dist-info/AUTHORS.rst
invenio_explicit_acls-4.5.0.dist-info/LICENSE
invenio_explicit_acls-4.5.0.dist-info/METADATA
invenio_explicit_acls-4.5.0.dist-info/WHEEL
invenio_explicit_acls-4.5.0.dist-info/entry_points.txt
invenio_explicit_acls-4.5.0.dist-info/top_level.txt
invenio_explicit_acls-4.5.0.dist-info/RECORD
