Metadata-Version: 2.1
Name: invenio-explicit-acls
Version: 4.5.0
Summary: Data model for CIS theses repository
Home-page: https://github.com/oarepo/invenio-explicit-acls
Author: CIS UCT Prague
Author-email: simeki@vscht.cz
License: MIT
Keywords: invenio-explicit-acls Invenio declarative ACL
Platform: any
Classifier: Environment :: Web Environment
Classifier: Intended Audience :: Developers
Classifier: License :: OSI Approved :: MIT License
Classifier: Operating System :: OS Independent
Classifier: Programming Language :: Python
Classifier: Topic :: Internet :: WWW/HTTP :: Dynamic Content
Classifier: Topic :: Software Development :: Libraries :: Python Modules
Classifier: Programming Language :: Python :: 2
Classifier: Programming Language :: Python :: 2.7
Classifier: Programming Language :: Python :: 3
Classifier: Programming Language :: Python :: 3.5
Classifier: Development Status :: 4 - Beta
Requires-Dist: invenio-oarepo-invenio-model (>=1.2)
Provides-Extra: docs
Requires-Dist: Sphinx (>=1.5.1) ; extra == 'docs'
Requires-Dist: sphinxcontrib-httpdomain (>=1.7.0) ; extra == 'docs'
Provides-Extra: tests
Requires-Dist: oarepo[tests] (~=3.2.0) ; extra == 'tests'
Provides-Extra: tests-es7
Requires-Dist: oarepo[tests-es7] (~=3.2.0) ; extra == 'tests-es7'
